README.rst
setup.py
bin/shuttertalk
shuttertalk/__init__.py
shuttertalk.egg-info/PKG-INFO
shuttertalk.egg-info/SOURCES.txt
shuttertalk.egg-info/dependency_links.txt
shuttertalk.egg-info/requires.txt
shuttertalk.egg-info/top_level.txt