Metadata-Version: 1.0
Name: shuttertalk
Version: 0.2
Summary: something
Home-page: http://lav.io
Author: Sam
Author-email: lavigne@nyu.edu
License: GPL
Platform: UNKNOWN
